algoinfinite/__init__.py
algoinfinite/main.py
algoinfinite/algorithms/__init__.py
algoinfinite/algorithms/graph.py
algoinfinite/algorithms/math.py
algoinfinite/algorithms/searching.py
algoinfinite/algorithms/sorting.py
algoinfinite/data_structures/__init__.py
algoinfinite/data_structures/linked_list.py
algoinfinite/data_structures/stack.py
algoinfinite-0.2.1.dist-info/LICENSE
algoinfinite-0.2.1.dist-info/METADATA
algoinfinite-0.2.1.dist-info/WHEEL
algoinfinite-0.2.1.dist-info/entry_points.txt
algoinfinite-0.2.1.dist-info/top_level.txt
algoinfinite-0.2.1.dist-info/RECORD
