Metadata-Version: 2.1
Name: algoinfinite
Version: 0.2.1
Summary: A collection of algorithms and data structures in Python.
Home-page: https://github.com/Madan1500/algoinfinite
Author: Madan Mohan Behera
Author-email: madanmohan14072002@gmail.com
License: MIT
Keywords: algorithms,data structures,python,algoinfinite,sorting,searching,dynamic programming,greedy algorithms
Platform: UNKNOWN
Classifier: Development Status :: 4 - Beta
Classifier: Intended Audience :: Developers
Classifier: License :: OSI Approved :: MIT License
Classifier: Programming Language :: Python :: 3
Classifier: Programming Language :: Python :: 3.6
Classifier: Programming Language :: Python :: 3.7
Classifier: Programming Language :: Python :: 3.8
Classifier: Programming Language :: Python :: 3.9
Classifier: Topic :: Software Development :: Libraries
Classifier: Topic :: Software Development :: Libraries :: Python Modules
Requires-Python: >=3.6
License-File: LICENSE
